jibe/__init__.py
jibe/app.css
jibe/app.js
jibe/app.py
jibe/page.html
jibe/page.py
jibe/widget.py
jibe/lib/backbone.js
jibe/lib/handlebars.js
jibe/lib/jquery-1.12.4.js
jibe/lib/underscore.js
jibe-0.1.3.dist-info/LICENSE.txt
jibe-0.1.3.dist-info/METADATA
jibe-0.1.3.dist-info/WHEEL
jibe-0.1.3.dist-info/top_level.txt
jibe-0.1.3.dist-info/RECORD
