Metadata-Version: 2.1
Name: jibe
Version: 0.1.3
Summary: Pure-Python Full-Stack Web Framework
Home-page: http://jibe.caram.cl
Author: Juan Pablo Caram
Author-email: jpcaram@gmail.com
License: UNKNOWN
Platform: UNKNOWN
Requires: tornado
Requires: jinja2
Requires: matplotlib
Requires: numpy
Requires-Python: >=3.6
Requires-Dist: tornado
Requires-Dist: jinja2
